dodo_webdev_commands/__init__.py
dodo_webdev_commands/_docker_update.py
dodo_webdev_commands/aws-connect.py
dodo_webdev_commands/django-manage.py
dodo_webdev_commands/download-dump.py
dodo_webdev_commands/kubectl-cp.py
dodo_webdev_commands/make.py
dodo_webdev_commands/node.py
dodo_webdev_commands/npm-link.py
dodo_webdev_commands/npm-publish.py
dodo_webdev_commands/prod-to-staging.py
dodo_webdev_commands/pytest.py
dodo_webdev_commands/tsc.py
dodo_webdev_commands-0.21.0.dist-info/LICENSE
dodo_webdev_commands-0.21.0.dist-info/METADATA
dodo_webdev_commands-0.21.0.dist-info/WHEEL
dodo_webdev_commands-0.21.0.dist-info/top_level.txt
dodo_webdev_commands-0.21.0.dist-info/RECORD
