Metadata-Version: 2.1
Name: dodo-webdev-commands
Version: 0.21.0
Summary: Web development related Dodo Commands
Home-page: https://github.com/mnieber/dodo-webdev-commands
Download-URL: https://github.com/mnieber/dodo-webdev-commands/tarball/0.21.0
Author: Maarten Nieber
Author-email: hallomaarten@yahoo.com
License: MIT
License-File: LICENSE
